usgs_quake/__init__.py
usgs_quake-1.0.2.dist-info/LICENSE
usgs_quake-1.0.2.dist-info/METADATA
usgs_quake-1.0.2.dist-info/WHEEL
usgs_quake-1.0.2.dist-info/top_level.txt
usgs_quake-1.0.2.dist-info/RECORD
